pydba/__init__.py
pydba/exc.py
pydba/postgres.py
pydba/utils.py
pydba-1.2.1.dist-info/DESCRIPTION.rst
pydba-1.2.1.dist-info/METADATA
pydba-1.2.1.dist-info/RECORD
pydba-1.2.1.dist-info/WHEEL
pydba-1.2.1.dist-info/metadata.json
pydba-1.2.1.dist-info/top_level.txt
tests/__init__.py
tests/pydba/__init__.py
tests/pydba/test_postgres.py
tests/pydba/test_utils.py
